[
    {
        "name": "Scholarship For Top Class Education For Students With Disabilities",
        "description": "Scholarship details for Scholarship For Top Class Education For Students With Disabilities",
        "category": "N/A",
        "level": "N/A",
        "institute": "N/A",
        "ministry": "Department of Empowerment of Persons with Disabilities",
        "eligibility": {
            "academicCriteria": "N/A",
            "incomeCriteria": "N/A",
            "categoryCriteria": "N/A",
            "gender": "ALL",
            "ageLimit": null
        },
        "applicationDetails": {
            "startDate": null,
            "endDate": {},
            "status": "Closed",
            "applyLink": "https://scholarships.gov.in/public/schemeGuidelines/DEPDGuidelines_1.pdf",
            "requiredDocuments": [],
            "applicationFee": 0
        },
        "benefits": {
            "amount": null,
            "duration": "N/A",
            "renewable": false,
            "benefits": "N/A"
        },
        "selectionProcess": {
            "selectionProcess": "N/A",
            "examRequired": false,
            "interviewRequired": false,
            "resultDate": null
        },
        "contactDetails": {
            "officialWebsite": "https://scholarships.gov.in",
            "helplineNumber": null,
            "email": "N/A"
        }
    },
    {
        "name": "Pre Matric Scholarship For Students With Disabilities",
        "description": "Scholarship details for Pre Matric Scholarship For Students With Disabilities",
        "category": "N/A",
        "level": "N/A",
        "institute": "N/A",
        "ministry": "Department of Empowerment of Persons with Disabilities",
        "eligibility": {
            "academicCriteria": "N/A",
            "incomeCriteria": "N/A",
            "categoryCriteria": "N/A",
            "gender": "ALL",
            "ageLimit": null
        },
        "applicationDetails": {
            "startDate": null,
            "endDate": {},
            "status": "Closed",
            "applyLink": "https://scholarships.gov.in/public/schemeGuidelines/DEPDGuidelines_1.pdf",
            "requiredDocuments": [],
            "applicationFee": 0
        },
        "benefits": {
            "amount": null,
            "duration": "N/A",
            "renewable": false,
            "benefits": "N/A"
        },
        "selectionProcess": {
            "selectionProcess": "N/A",
            "examRequired": false,
            "interviewRequired": false,
            "resultDate": null
        },
        "contactDetails": {
            "officialWebsite": "https://scholarships.gov.in",
            "helplineNumber": null,
            "email": "N/A"
        }
    },
    {
        "name": "Post Matric Scholarship For Students With Disabilities",
        "description": "Scholarship details for Post Matric Scholarship For Students With Disabilities",
        "category": "N/A",
        "level": "N/A",
        "institute": "N/A",
        "ministry": "Department of Empowerment of Persons with Disabilities",
        "eligibility": {
            "academicCriteria": "N/A",
            "incomeCriteria": "N/A",
            "categoryCriteria": "N/A",
            "gender": "ALL",
            "ageLimit": null
        },
        "applicationDetails": {
            "startDate": null,
            "endDate": {},
            "status": "Closed",
            "applyLink": "https://scholarships.gov.in/public/schemeGuidelines/DEPDGuidelines_1.pdf",
            "requiredDocuments": [],
            "applicationFee": 0
        },
        "benefits": {
            "amount": null,
            "duration": "N/A",
            "renewable": false,
            "benefits": "N/A"
        },
        "selectionProcess": {
            "selectionProcess": "N/A",
            "examRequired": false,
            "interviewRequired": false,
            "resultDate": null
        },
        "contactDetails": {
            "officialWebsite": "https://scholarships.gov.in",
            "helplineNumber": null,
            "email": "N/A"
        }
    },
    {
        "name": "Central Sector Scheme Of Scholarships For College And University Students",
        "description": "Scholarship details for Central Sector Scheme Of Scholarships For College And University Students",
        "category": "N/A",
        "level": "N/A",
        "institute": "N/A",
        "ministry": "Department of Higher Education",
        "eligibility": {
            "academicCriteria": "N/A",
            "incomeCriteria": "N/A",
            "categoryCriteria": "N/A",
            "gender": "ALL",
            "ageLimit": null
        },
        "applicationDetails": {
            "startDate": null,
            "endDate": {},
            "status": "Closed",
            "applyLink": "https://scholarships.gov.in/public/schemeGuidelines/CSSS_GUIDLINES_07022024_updated.pdf",
            "requiredDocuments": [],
            "applicationFee": 0
        },
        "benefits": {
            "amount": null,
            "duration": "N/A",
            "renewable": false,
            "benefits": "N/A"
        },
        "selectionProcess": {
            "selectionProcess": "N/A",
            "examRequired": false,
            "interviewRequired": false,
            "resultDate": null
        },
        "contactDetails": {
            "officialWebsite": "https://scholarships.gov.in",
            "helplineNumber": null,
            "email": "N/A"
        }
    },
    {
        "name": "National Fellowship And Scholarship For Higher Education Of St Students - Scholarship (Formally Top Class Education For Schedule Tribe Students)",
        "description": "Scholarship details for National Fellowship And Scholarship For Higher Education Of St Students - Scholarship (Formally Top Class Education For Schedule Tribe Students)",
        "category": "N/A",
        "level": "N/A",
        "institute": "N/A",
        "ministry": "Ministry of Tribal Affairs",
        "eligibility": {
            "academicCriteria": "N/A",
            "incomeCriteria": "N/A",
            "categoryCriteria": "N/A",
            "gender": "ALL",
            "ageLimit": null
        },
        "applicationDetails": {
            "startDate": null,
            "endDate": {},
            "status": "Closed",
            "applyLink": "https://scholarships.gov.in/public/schemeGuidelines/tribalfellowshipguideline.pdf",
            "requiredDocuments": [],
            "applicationFee": 0
        },
        "benefits": {
            "amount": null,
            "duration": "N/A",
            "renewable": false,
            "benefits": "N/A"
        },
        "selectionProcess": {
            "selectionProcess": "N/A",
            "examRequired": false,
            "interviewRequired": false,
            "resultDate": null
        },
        "contactDetails": {
            "officialWebsite": "https://scholarships.gov.in",
            "helplineNumber": null,
            "email": "N/A"
        }
    },
    {
        "name": "Merit-Cum-Means Scholarship For Professional And Technical Courses Cs",
        "description": "Scholarship details for Merit-Cum-Means Scholarship For Professional And Technical Courses Cs",
        "category": "N/A",
        "level": "N/A",
        "institute": "N/A",
        "ministry": "Ministry of Minority Affairs",
        "eligibility": {
            "academicCriteria": "N/A",
            "incomeCriteria": "N/A",
            "categoryCriteria": "N/A",
            "gender": "ALL",
            "ageLimit": null
        },
        "applicationDetails": {
            "startDate": null,
            "endDate": {},
            "status": "Closed",
            "applyLink": "https://scholarships.gov.in/public/schemeGuidelines/MoMA_MCM_2018-20.pdf",
            "requiredDocuments": [],
            "applicationFee": 0
        },
        "benefits": {
            "amount": null,
            "duration": "N/A",
            "renewable": false,
            "benefits": "N/A"
        },
        "selectionProcess": {
            "selectionProcess": "N/A",
            "examRequired": false,
            "interviewRequired": false,
            "resultDate": null
        },
        "contactDetails": {
            "officialWebsite": "https://scholarships.gov.in",
            "helplineNumber": null,
            "email": "N/A"
        }
    },
    {
        "name": "Pre Matric Scholarships For Minority",
        "description": "Scholarship details for Pre Matric Scholarships For Minority",
        "category": "N/A",
        "level": "N/A",
        "institute": "N/A",
        "ministry": "Ministry of Minority Affairs",
        "eligibility": {
            "academicCriteria": "N/A",
            "incomeCriteria": "N/A",
            "categoryCriteria": "N/A",
            "gender": "ALL",
            "ageLimit": null
        },
        "applicationDetails": {
            "startDate": null,
            "endDate": {},
            "status": "Closed",
            "applyLink": "https://scholarships.gov.in/public/schemeGuidelines/MoMA_Pre_Matric_2018-20.pdf",
            "requiredDocuments": [],
            "applicationFee": 0
        },
        "benefits": {
            "amount": null,
            "duration": "N/A",
            "renewable": false,
            "benefits": "N/A"
        },
        "selectionProcess": {
            "selectionProcess": "N/A",
            "examRequired": false,
            "interviewRequired": false,
            "resultDate": null
        },
        "contactDetails": {
            "officialWebsite": "https://scholarships.gov.in",
            "helplineNumber": null,
            "email": "N/A"
        }
    },
    {
        "name": "Post Matric Scholarship Schemes Minorities Cs",
        "description": "Scholarship details for Post Matric Scholarship Schemes Minorities Cs",
        "category": "N/A",
        "level": "N/A",
        "institute": "N/A",
        "ministry": "Ministry of Minority Affairs",
        "eligibility": {
            "academicCriteria": "N/A",
            "incomeCriteria": "N/A",
            "categoryCriteria": "N/A",
            "gender": "ALL",
            "ageLimit": null
        },
        "applicationDetails": {
            "startDate": null,
            "endDate": {},
            "status": "Closed",
            "applyLink": "https://scholarships.gov.in/public/schemeGuidelines/MoMA_Post_Matric_2018-20.pdf",
            "requiredDocuments": [],
            "applicationFee": 0
        },
        "benefits": {
            "amount": null,
            "duration": "N/A",
            "renewable": false,
            "benefits": "N/A"
        },
        "selectionProcess": {
            "selectionProcess": "N/A",
            "examRequired": false,
            "interviewRequired": false,
            "resultDate": null
        },
        "contactDetails": {
            "officialWebsite": "https://scholarships.gov.in",
            "helplineNumber": null,
            "email": "N/A"
        }
    },
    {
        "name": "National Means Cum Merit Scholarship",
        "description": "Scholarship details for National Means Cum Merit Scholarship",
        "category": "N/A",
        "level": "N/A",
        "institute": "N/A",
        "ministry": "Department of School Education & Literacy",
        "eligibility": {
            "academicCriteria": "N/A",
            "incomeCriteria": "N/A",
            "categoryCriteria": "N/A",
            "gender": "ALL",
            "ageLimit": null
        },
        "applicationDetails": {
            "startDate": null,
            "endDate": {},
            "status": "Closed",
            "applyLink": "https://scholarships.gov.in/public/schemeGuidelines/NMMSSGuidelines.pdf",
            "requiredDocuments": [],
            "applicationFee": 0
        },
        "benefits": {
            "amount": null,
            "duration": "N/A",
            "renewable": false,
            "benefits": "N/A"
        },
        "selectionProcess": {
            "selectionProcess": "N/A",
            "examRequired": false,
            "interviewRequired": false,
            "resultDate": null
        },
        "contactDetails": {
            "officialWebsite": "https://scholarships.gov.in",
            "helplineNumber": null,
            "email": "N/A"
        }
    },
    {
        "name": "Prime Minister'S Scholarship Scheme For Central Armed Police Forces And Assam Rifles",
        "description": "Scholarship details for Prime Minister'S Scholarship Scheme For Central Armed Police Forces And Assam Rifles",
        "category": "N/A",
        "level": "N/A",
        "institute": "N/A",
        "ministry": "Ministry of Home Affairs",
        "eligibility": {
            "academicCriteria": "N/A",
            "incomeCriteria": "N/A",
            "categoryCriteria": "N/A",
            "gender": "ALL",
            "ageLimit": null
        },
        "applicationDetails": {
            "startDate": null,
            "endDate": {},
            "status": "Closed",
            "applyLink": "https://scholarships.gov.in/public/schemeGuidelines/warb/PMSS_Guidelines_1197_3001-2023-24.pdf",
            "requiredDocuments": [],
            "applicationFee": 0
        },
        "benefits": {
            "amount": null,
            "duration": "N/A",
            "renewable": false,
            "benefits": "N/A"
        },
        "selectionProcess": {
            "selectionProcess": "N/A",
            "examRequired": false,
            "interviewRequired": false,
            "resultDate": null
        },
        "contactDetails": {
            "officialWebsite": "https://scholarships.gov.in",
            "helplineNumber": null,
            "email": "N/A"
        }
    },
    {
        "name": "Prime Minister'S Scholarship Scheme For Wards Of States/Uts  Police Personnel Martyred During Terror/Naxal Attacks",
        "description": "Scholarship details for Prime Minister'S Scholarship Scheme For Wards Of States/Uts  Police Personnel Martyred During Terror/Naxal Attacks",
        "category": "N/A",
        "level": "N/A",
        "institute": "N/A",
        "ministry": "Ministry of Home Affairs",
        "eligibility": {
            "academicCriteria": "N/A",
            "incomeCriteria": "N/A",
            "categoryCriteria": "N/A",
            "gender": "ALL",
            "ageLimit": null
        },
        "applicationDetails": {
            "startDate": null,
            "endDate": {},
            "status": "Closed",
            "applyLink": "https://scholarships.gov.in/public/schemeGuidelines/warb/PMSS_Guidelines_1197_3001-2023-24.pdf",
            "requiredDocuments": [],
            "applicationFee": 0
        },
        "benefits": {
            "amount": null,
            "duration": "N/A",
            "renewable": false,
            "benefits": "N/A"
        },
        "selectionProcess": {
            "selectionProcess": "N/A",
            "examRequired": false,
            "interviewRequired": false,
            "resultDate": null
        },
        "contactDetails": {
            "officialWebsite": "https://scholarships.gov.in",
            "helplineNumber": null,
            "email": "N/A"
        }
    },
    {
        "name": "Prime Minister'S Scholarship Scheme For Ministry Of Railways",
        "description": "Scholarship details for Prime Minister'S Scholarship Scheme For Ministry Of Railways",
        "category": "N/A",
        "level": "N/A",
        "institute": "N/A",
        "ministry": "Ministry of Railways (Railway Board)",
        "eligibility": {
            "academicCriteria": "N/A",
            "incomeCriteria": "N/A",
            "categoryCriteria": "N/A",
            "gender": "ALL",
            "ageLimit": null
        },
        "applicationDetails": {
            "startDate": null,
            "endDate": {},
            "status": "Closed",
            "applyLink": "https://scholarships.gov.in/public/schemeGuidelines/MORB_GL.pdf",
            "requiredDocuments": [],
            "applicationFee": 0
        },
        "benefits": {
            "amount": null,
            "duration": "N/A",
            "renewable": false,
            "benefits": "N/A"
        },
        "selectionProcess": {
            "selectionProcess": "N/A",
            "examRequired": false,
            "interviewRequired": false,
            "resultDate": null
        },
        "contactDetails": {
            "officialWebsite": "https://scholarships.gov.in",
            "helplineNumber": null,
            "email": "N/A"
        }
    },
    {
        "name": "Aicte - Swanath Scholarship Scheme (Technical Diploma)",
        "description": "Scholarship details for Aicte - Swanath Scholarship Scheme (Technical Diploma)",
        "category": "N/A",
        "level": "N/A",
        "institute": "N/A",
        "ministry": "All India Council For Technical Education",
        "eligibility": {
            "academicCriteria": "N/A",
            "incomeCriteria": "N/A",
            "categoryCriteria": "N/A",
            "gender": "ALL",
            "ageLimit": null
        },
        "applicationDetails": {
            "startDate": null,
            "endDate": {},
            "status": "Closed",
            "applyLink": "https://scholarships.gov.in/public/schemeGuidelines/AICTE/AICTE_3038_G.pdf",
            "requiredDocuments": [],
            "applicationFee": 0
        },
        "benefits": {
            "amount": null,
            "duration": "N/A",
            "renewable": false,
            "benefits": "N/A"
        },
        "selectionProcess": {
            "selectionProcess": "N/A",
            "examRequired": false,
            "interviewRequired": false,
            "resultDate": null
        },
        "contactDetails": {
            "officialWebsite": "https://scholarships.gov.in",
            "helplineNumber": null,
            "email": "N/A"
        }
    },
    {
        "name": "Pm Usp Special Scholarship Scheme For Jammu Kashmir And Ladakh",
        "description": "Scholarship details for Pm Usp Special Scholarship Scheme For Jammu Kashmir And Ladakh",
        "category": "N/A",
        "level": "N/A",
        "institute": "N/A",
        "ministry": "All India Council For Technical Education",
        "eligibility": {
            "academicCriteria": "N/A",
            "incomeCriteria": "N/A",
            "categoryCriteria": "N/A",
            "gender": "ALL",
            "ageLimit": null
        },
        "applicationDetails": {
            "startDate": null,
            "endDate": {},
            "status": "Closed",
            "applyLink": "N/A",
            "requiredDocuments": [],
            "applicationFee": 0
        },
        "benefits": {
            "amount": null,
            "duration": "N/A",
            "renewable": false,
            "benefits": "N/A"
        },
        "selectionProcess": {
            "selectionProcess": "N/A",
            "examRequired": false,
            "interviewRequired": false,
            "resultDate": null
        },
        "contactDetails": {
            "officialWebsite": "https://scholarships.gov.in",
            "helplineNumber": null,
            "email": "N/A"
        }
    },
    {
        "name": "Aicte - Swanath Scholarship Scheme ( Technical Degree)",
        "description": "Scholarship details for Aicte - Swanath Scholarship Scheme ( Technical Degree)",
        "category": "N/A",
        "level": "N/A",
        "institute": "N/A",
        "ministry": "All India Council For Technical Education",
        "eligibility": {
            "academicCriteria": "N/A",
            "incomeCriteria": "N/A",
            "categoryCriteria": "N/A",
            "gender": "ALL",
            "ageLimit": null
        },
        "applicationDetails": {
            "startDate": null,
            "endDate": {},
            "status": "Closed",
            "applyLink": "https://scholarships.gov.in/public/schemeGuidelines/AICTE/AICTE_3039_G.pdf",
            "requiredDocuments": [],
            "applicationFee": 0
        },
        "benefits": {
            "amount": null,
            "duration": "N/A",
            "renewable": false,
            "benefits": "N/A"
        },
        "selectionProcess": {
            "selectionProcess": "N/A",
            "examRequired": false,
            "interviewRequired": false,
            "resultDate": null
        },
        "contactDetails": {
            "officialWebsite": "https://scholarships.gov.in",
            "helplineNumber": null,
            "email": "N/A"
        }
    },
    {
        "name": "Aicte - Pragati Scholarship Scheme For Girl Students  ( Technical Diploma)",
        "description": "Scholarship details for Aicte - Pragati Scholarship Scheme For Girl Students  ( Technical Diploma)",
        "category": "N/A",
        "level": "N/A",
        "institute": "N/A",
        "ministry": "All India Council For Technical Education",
        "eligibility": {
            "academicCriteria": "N/A",
            "incomeCriteria": "N/A",
            "categoryCriteria": "N/A",
            "gender": "ALL",
            "ageLimit": null
        },
        "applicationDetails": {
            "startDate": null,
            "endDate": {},
            "status": "Closed",
            "applyLink": "https://scholarships.gov.in/public/schemeGuidelines/AICTE/AICTE_2011_G.pdf",
            "requiredDocuments": [],
            "applicationFee": 0
        },
        "benefits": {
            "amount": null,
            "duration": "N/A",
            "renewable": false,
            "benefits": "N/A"
        },
        "selectionProcess": {
            "selectionProcess": "N/A",
            "examRequired": false,
            "interviewRequired": false,
            "resultDate": null
        },
        "contactDetails": {
            "officialWebsite": "https://scholarships.gov.in",
            "helplineNumber": null,
            "email": "N/A"
        }
    },
    {
        "name": "Aicte - Saksham Scholarship Scheme For Specially Abled Student ( Technical Degree)",
        "description": "Scholarship details for Aicte - Saksham Scholarship Scheme For Specially Abled Student ( Technical Degree)",
        "category": "N/A",
        "level": "N/A",
        "institute": "N/A",
        "ministry": "All India Council For Technical Education",
        "eligibility": {
            "academicCriteria": "N/A",
            "incomeCriteria": "N/A",
            "categoryCriteria": "N/A",
            "gender": "ALL",
            "ageLimit": null
        },
        "applicationDetails": {
            "startDate": null,
            "endDate": {},
            "status": "Closed",
            "applyLink": "https://scholarships.gov.in/public/schemeGuidelines/AICTE/AICTE_2012_G.pdf",
            "requiredDocuments": [],
            "applicationFee": 0
        },
        "benefits": {
            "amount": null,
            "duration": "N/A",
            "renewable": false,
            "benefits": "N/A"
        },
        "selectionProcess": {
            "selectionProcess": "N/A",
            "examRequired": false,
            "interviewRequired": false,
            "resultDate": null
        },
        "contactDetails": {
            "officialWebsite": "https://scholarships.gov.in",
            "helplineNumber": null,
            "email": "N/A"
        }
    },
    {
        "name": "Aicte - Pragati Scholarship Scheme For Girl Students ( Technical Degree)",
        "description": "Scholarship details for Aicte - Pragati Scholarship Scheme For Girl Students ( Technical Degree)",
        "category": "N/A",
        "level": "N/A",
        "institute": "N/A",
        "ministry": "All India Council For Technical Education",
        "eligibility": {
            "academicCriteria": "N/A",
            "incomeCriteria": "N/A",
            "categoryCriteria": "N/A",
            "gender": "ALL",
            "ageLimit": null
        },
        "applicationDetails": {
            "startDate": null,
            "endDate": {},
            "status": "Closed",
            "applyLink": "https://scholarships.gov.in/public/schemeGuidelines/AICTE/AICTE_2010_G.pdf",
            "requiredDocuments": [],
            "applicationFee": 0
        },
        "benefits": {
            "amount": null,
            "duration": "N/A",
            "renewable": false,
            "benefits": "N/A"
        },
        "selectionProcess": {
            "selectionProcess": "N/A",
            "examRequired": false,
            "interviewRequired": false,
            "resultDate": null
        },
        "contactDetails": {
            "officialWebsite": "https://scholarships.gov.in",
            "helplineNumber": null,
            "email": "N/A"
        }
    },
    {
        "name": "Aicte - Saksham Scholarship Scheme For Specially Abled Student ( Technical Diploma)",
        "description": "Scholarship details for Aicte - Saksham Scholarship Scheme For Specially Abled Student ( Technical Diploma)",
        "category": "N/A",
        "level": "N/A",
        "institute": "N/A",
        "ministry": "All India Council For Technical Education",
        "eligibility": {
            "academicCriteria": "N/A",
            "incomeCriteria": "N/A",
            "categoryCriteria": "N/A",
            "gender": "ALL",
            "ageLimit": null
        },
        "applicationDetails": {
            "startDate": null,
            "endDate": {},
            "status": "Closed",
            "applyLink": "https://scholarships.gov.in/public/schemeGuidelines/AICTE/AICTE_2013_G.pdf",
            "requiredDocuments": [],
            "applicationFee": 0
        },
        "benefits": {
            "amount": null,
            "duration": "N/A",
            "renewable": false,
            "benefits": "N/A"
        },
        "selectionProcess": {
            "selectionProcess": "N/A",
            "examRequired": false,
            "interviewRequired": false,
            "resultDate": null
        },
        "contactDetails": {
            "officialWebsite": "https://scholarships.gov.in",
            "helplineNumber": null,
            "email": "N/A"
        }
    },
    {
        "name": "National Scholarship For Post Graduate Studies",
        "description": "Scholarship details for National Scholarship For Post Graduate Studies",
        "category": "N/A",
        "level": "N/A",
        "institute": "N/A",
        "ministry": "UGC",
        "eligibility": {
            "academicCriteria": "N/A",
            "incomeCriteria": "N/A",
            "categoryCriteria": "N/A",
            "gender": "ALL",
            "ageLimit": null
        },
        "applicationDetails": {
            "startDate": null,
            "endDate": {},
            "status": "Closed",
            "applyLink": "https://scholarships.gov.in/public/schemeGuidelines/Guidelines_NATIONAL_SCHOLARSHIP_FOR_POSTGRADUATE_STUDIES_UGC_2324.pdf",
            "requiredDocuments": [],
            "applicationFee": 0
        },
        "benefits": {
            "amount": null,
            "duration": "N/A",
            "renewable": false,
            "benefits": "N/A"
        },
        "selectionProcess": {
            "selectionProcess": "N/A",
            "examRequired": false,
            "interviewRequired": false,
            "resultDate": null
        },
        "contactDetails": {
            "officialWebsite": "https://scholarships.gov.in",
            "helplineNumber": null,
            "email": "N/A"
        }
    },
    {
        "name": "Ishan Uday Special Scholarship Scheme For Ner",
        "description": "Scholarship details for Ishan Uday Special Scholarship Scheme For Ner",
        "category": "N/A",
        "level": "N/A",
        "institute": "N/A",
        "ministry": "UGC",
        "eligibility": {
            "academicCriteria": "N/A",
            "incomeCriteria": "N/A",
            "categoryCriteria": "N/A",
            "gender": "ALL",
            "ageLimit": null
        },
        "applicationDetails": {
            "startDate": null,
            "endDate": {},
            "status": "Closed",
            "applyLink": "https://scholarships.gov.in/public/schemeGuidelines/Guidelines_ISHAN%20UDAY_2324.pdf",
            "requiredDocuments": [],
            "applicationFee": 0
        },
        "benefits": {
            "amount": null,
            "duration": "N/A",
            "renewable": false,
            "benefits": "N/A"
        },
        "selectionProcess": {
            "selectionProcess": "N/A",
            "examRequired": false,
            "interviewRequired": false,
            "resultDate": null
        },
        "contactDetails": {
            "officialWebsite": "https://scholarships.gov.in",
            "helplineNumber": null,
            "email": "N/A"
        }
    },
    {
        "name": "Financial Support To The Students Of Ner For Higher Professional Courses(Nec Merit Scholarship)",
        "description": "Scholarship details for Financial Support To The Students Of Ner For Higher Professional Courses(Nec Merit Scholarship)",
        "category": "N/A",
        "level": "N/A",
        "institute": "N/A",
        "ministry": "North Eastern Council(NEC),DoNER",
        "eligibility": {
            "academicCriteria": "N/A",
            "incomeCriteria": "N/A",
            "categoryCriteria": "N/A",
            "gender": "ALL",
            "ageLimit": null
        },
        "applicationDetails": {
            "startDate": null,
            "endDate": {},
            "status": "Closed",
            "applyLink": "https://scholarships.gov.in/public/schemeGuidelines/NEC_1234_G.pdf",
            "requiredDocuments": [],
            "applicationFee": 0
        },
        "benefits": {
            "amount": null,
            "duration": "N/A",
            "renewable": false,
            "benefits": "N/A"
        },
        "selectionProcess": {
            "selectionProcess": "N/A",
            "examRequired": false,
            "interviewRequired": false,
            "resultDate": null
        },
        "contactDetails": {
            "officialWebsite": "https://scholarships.gov.in",
            "helplineNumber": null,
            "email": "N/A"
        }
    },
    {
        "name": "Central Sector Scholarship Of Top Class Education For Sc Students",
        "description": "Scholarship details for Central Sector Scholarship Of Top Class Education For Sc Students",
        "category": "N/A",
        "level": "N/A",
        "institute": "N/A",
        "ministry": "Department of Social Justice & Empowerment",
        "eligibility": {
            "academicCriteria": "N/A",
            "incomeCriteria": "N/A",
            "categoryCriteria": "N/A",
            "gender": "ALL",
            "ageLimit": null
        },
        "applicationDetails": {
            "startDate": null,
            "endDate": {},
            "status": "Closed",
            "applyLink": "https://scholarships.gov.in/public/schemeGuidelines/Top_Class_Education_Scheme_2018.pdf",
            "requiredDocuments": [],
            "applicationFee": 0
        },
        "benefits": {
            "amount": null,
            "duration": "N/A",
            "renewable": false,
            "benefits": "N/A"
        },
        "selectionProcess": {
            "selectionProcess": "N/A",
            "examRequired": false,
            "interviewRequired": false,
            "resultDate": null
        },
        "contactDetails": {
            "officialWebsite": "https://scholarships.gov.in",
            "helplineNumber": null,
            "email": "N/A"
        }
    },
    {
        "name": "Financial Assistance For Education To The Wards Of Beedi/Cine/Iomc/Lsdm- Pre Matric",
        "description": "Scholarship details for Financial Assistance For Education To The Wards Of Beedi/Cine/Iomc/Lsdm- Pre Matric",
        "category": "N/A",
        "level": "N/A",
        "institute": "N/A",
        "ministry": "Ministry of Labour & Employment",
        "eligibility": {
            "academicCriteria": "N/A",
            "incomeCriteria": "N/A",
            "categoryCriteria": "N/A",
            "gender": "ALL",
            "ageLimit": null
        },
        "applicationDetails": {
            "startDate": null,
            "endDate": {},
            "status": "Closed",
            "applyLink": "https://scholarships.gov.in/public/schemeGuidelines/Labour_Ministry_Guidelines_of_scholarhsips%20schemes.pdf",
            "requiredDocuments": [],
            "applicationFee": 0
        },
        "benefits": {
            "amount": null,
            "duration": "N/A",
            "renewable": false,
            "benefits": "N/A"
        },
        "selectionProcess": {
            "selectionProcess": "N/A",
            "examRequired": false,
            "interviewRequired": false,
            "resultDate": null
        },
        "contactDetails": {
            "officialWebsite": "https://scholarships.gov.in",
            "helplineNumber": null,
            "email": "N/A"
        }
    },
    {
        "name": "Financial Assistance For Education To The Wards Of Beedi/Cine/Iomc/Lsdm- Post Matric",
        "description": "Scholarship details for Financial Assistance For Education To The Wards Of Beedi/Cine/Iomc/Lsdm- Post Matric",
        "category": "N/A",
        "level": "N/A",
        "institute": "N/A",
        "ministry": "Ministry of Labour & Employment",
        "eligibility": {
            "academicCriteria": "N/A",
            "incomeCriteria": "N/A",
            "categoryCriteria": "N/A",
            "gender": "ALL",
            "ageLimit": null
        },
        "applicationDetails": {
            "startDate": null,
            "endDate": {},
            "status": "Closed",
            "applyLink": "https://scholarships.gov.in/public/schemeGuidelines/Labour_Ministry_Guidelines_of_scholarhsips%20schemes.pdf",
            "requiredDocuments": [],
            "applicationFee": 0
        },
        "benefits": {
            "amount": null,
            "duration": "N/A",
            "renewable": false,
            "benefits": "N/A"
        },
        "selectionProcess": {
            "selectionProcess": "N/A",
            "examRequired": false,
            "interviewRequired": false,
            "resultDate": null
        },
        "contactDetails": {
            "officialWebsite": "https://scholarships.gov.in",
            "helplineNumber": null,
            "email": "N/A"
        }
    },
    {
        "name": "Pm Yasasvi Central Sector  Scheme Of Top Class Education In Schools For Obc, Ebc And Dnt Students",
        "description": "Scholarship details for Pm Yasasvi Central Sector  Scheme Of Top Class Education In Schools For Obc, Ebc And Dnt Students",
        "category": "N/A",
        "level": "N/A",
        "institute": "N/A",
        "ministry": "Department of Social Justice & Empowerment(Backward Classes)",
        "eligibility": {
            "academicCriteria": "N/A",
            "incomeCriteria": "N/A",
            "categoryCriteria": "N/A",
            "gender": "ALL",
            "ageLimit": null
        },
        "applicationDetails": {
            "startDate": null,
            "endDate": {},
            "status": "Closed",
            "applyLink": "https://scholarships.gov.in/public/schemeGuidelines/3061_G.pdf",
            "requiredDocuments": [],
            "applicationFee": 0
        },
        "benefits": {
            "amount": null,
            "duration": "N/A",
            "renewable": false,
            "benefits": "N/A"
        },
        "selectionProcess": {
            "selectionProcess": "N/A",
            "examRequired": false,
            "interviewRequired": false,
            "resultDate": null
        },
        "contactDetails": {
            "officialWebsite": "https://scholarships.gov.in",
            "helplineNumber": null,
            "email": "N/A"
        }
    },
    {
        "name": "Pm Yasasvi Central Sector  Scheme Of Top Class Education In College For Obc, Ebc And Dnt Students",
        "description": "Scholarship details for Pm Yasasvi Central Sector  Scheme Of Top Class Education In College For Obc, Ebc And Dnt Students",
        "category": "N/A",
        "level": "N/A",
        "institute": "N/A",
        "ministry": "Department of Social Justice & Empowerment(Backward Classes)",
        "eligibility": {
            "academicCriteria": "N/A",
            "incomeCriteria": "N/A",
            "categoryCriteria": "N/A",
            "gender": "ALL",
            "ageLimit": null
        },
        "applicationDetails": {
            "startDate": null,
            "endDate": {},
            "status": "Closed",
            "applyLink": "https://scholarships.gov.in/public/schemeGuidelines/ApprovedmodifieddraftofTopClassCollege.pdf",
            "requiredDocuments": [],
            "applicationFee": 0
        },
        "benefits": {
            "amount": null,
            "duration": "N/A",
            "renewable": false,
            "benefits": "N/A"
        },
        "selectionProcess": {
            "selectionProcess": "N/A",
            "examRequired": false,
            "interviewRequired": false,
            "resultDate": null
        },
        "contactDetails": {
            "officialWebsite": "https://scholarships.gov.in",
            "helplineNumber": null,
            "email": "N/A"
        }
    }
]